Metadata-Version: 1.1
Name: cebpostagger
Version: 1.2
Summary: Rule-Based Cebuano POS Tagger Using Constraint-Based Grammar and Affixing Rules
Home-page: https://github.com/ajrequina/Cebuano-POS-Tagger
Author: Arjemariel Requina
Author-email: rjrequina@gmail.com
License: UNKNOWN
Download-URL: https://github.com/ajrequina/Cebuano-POS-Tagger/archive/1.0.tar.gz
Keywords: pos-tagger,cebuano-pos-tagger
Platform: UNKNOWN
